influxdbsyncer/__init__.py
influxdbsyncer/helper.py
influxdbsyncer/influxdbsyncer.conf
influxdbsyncer-0.1.data/scripts/influxdbsyncer
influxdbsyncer-0.1.dist-info/METADATA
influxdbsyncer-0.1.dist-info/RECORD
influxdbsyncer-0.1.dist-info/WHEEL
influxdbsyncer-0.1.dist-info/top_level.txt
